{
  "javascript.suggestionActions.enabled": false,
  "clangd.path": "/Users/nachiketpusalkar/.config/coc/extensions/coc-clangd-data/install/10.0.0/clangd_10.0.0/bin/clangd",
  "eslint.autoFixOnSave": true,
  "eslint.filetypes": [
    "javascript",
    "javascriptreact",
    "typescript",
    "typescriptreact"
  ],
  "coc.preferences.formatOnSaveFiletypes": [
    "javascript",
    "JSON",
    "javascriptreact",
    "typescript",
    "typescriptreact",
    "css",
    "markdown",
    "ruby"
  ],
  "tsserver.formatOnType": true,
  "coc.preferences.formatOnType": true,
  "snippets.extends": {
    "typescript": ["javascript"],
    "javascriptreact": ["javascript"]
  }
}
